LICENSE
README.md
setup.py
src/miniflask/__init__.py
src/miniflask/dummy.py
src/miniflask/event.py
src/miniflask/exceptions.py
src/miniflask/miniflask.py
src/miniflask/state.py
src/miniflask/util.py
src/miniflask.egg-info/PKG-INFO
src/miniflask.egg-info/SOURCES.txt
src/miniflask.egg-info/dependency_links.txt
src/miniflask.egg-info/requires.txt
src/miniflask.egg-info/top_level.txt
src/miniflask/definitions/__init__.py
src/miniflask/events/__init__.py
src/miniflask/info/__init__.py
src/miniflask/modules/__init__.py
src/miniflask/settings/__init__.py