Metadata-Version: 2.1
Name: miniflask
Version: 5.0.0
Summary: Small research-oriented hook-based plugin engine.
Home-page: https://github.com/da-h/miniflask
Author: David Hartmann
Maintainer: David Hartmann
License: MIT License
Keywords: miniflask,plugin-engine,plugin-system
Classifier: Development Status :: 4 - Beta
Classifier: Intended Audience :: Developers
Classifier: Intended Audience :: Science/Research
Classifier: Topic :: Scientific/Engineering
Classifier: Topic :: Software Development :: Libraries :: Application Frameworks
Classifier: Environment :: Console
Classifier: Operating System :: MacOS
Classifier: Operating System :: Microsoft :: Windows
Classifier: Operating System :: POSIX :: Linux
Classifier: Operating System :: Unix
Classifier: Programming Language :: Python :: 3
Classifier: Programming Language :: Python :: 3.6
Classifier: Programming Language :: Python :: 3.7
Classifier: Programming Language :: Python :: 3.8
Classifier: Programming Language :: Python :: 3.9
Classifier: License :: OSI Approved :: MIT License
Classifier: Operating System :: OS Independent
Requires-Python: >=3.6
License-File: LICENSE
